{
  "campaign_date": "2025-08-13T17:58:57.159685",
  "immediate_campaign": {
    "total_posts": 8,
    "total_engagement": 738,
    "total_reach": 14463,
    "platform": "Facebook",
    "campaign_focus": "SuperMega 25-agent optimization"
  },
  "weekly_calendar": [
    {
      "day": 1,
      "posts": [
        {
          "content": "\ud83d\udca1 Smart business chooses SuperMega: 91.7% more efficient, 95% cost reduction, 100% business-focused results.\n\n#AIStrategy #AutomationROI #TechInnovation #SuperMegaInc\n\n\ud83d\udd17 Learn more: supermega.dev",
          "platform": "Facebook",
          "timestamp": "2025-08-13T17:58:57.158680",
          "engagement_prediction": 169,
          "reach_prediction": 3602,
          "day": 1,
          "post_number": 1
        },
        {
          "content": "\ud83d\udcca Live stats: 942 social engagements today, 9,336 total reach. SuperMega AI working 24/7 for better results.\n\n#SuperMegaAI #AIAgents #BusinessAutomation #EfficiencyFirst\n\n\ud83d\udd17 Learn more: supermega.dev",
          "platform": "Facebook",
          "timestamp": "2025-08-13T17:58:57.158680",
          "engagement_prediction": 116,
          "reach_prediction": 3131,
          "day": 1,
          "post_number": 2
        }
      ],
      "daily_total": 2
    },
    {
      "day": 2,
      "posts": [
        {
          "content": "\ud83d\udca1 Smart business chooses SuperMega: 91.7% more efficient, 95% cost reduction, 100% business-focused results.\n\n#StrategicAI #CostOptimization #SuperMega #QualityOverQuantity\n\n\ud83d\udd17 Learn more: supermega.dev",
          "platform": "Facebook",
          "timestamp": "2025-08-13T17:58:57.158680",
          "engagement_prediction": 91,
          "reach_prediction": 1239,
          "day": 2,
          "post_number": 1
        },
        {
          "content": "\ud83d\ude80 SuperMega's 25 strategic AI agents outperform 300-agent systems by 91.7%! Quality over quantity wins every time.\n\n#SuperMegaAI #AIAgents #BusinessAutomation #EfficiencyFirst\n\n\ud83d\udd17 Learn more: supermega.dev",
          "platform": "Facebook",
          "timestamp": "2025-08-13T17:58:57.158680",
          "engagement_prediction": 61,
          "reach_prediction": 3711,
          "day": 2,
          "post_number": 2
        },
        {
          "content": "\ud83c\udfc6 The future is here: AI agents that think strategically, act efficiently, and deliver measurable business impact.\n\n#AIInnovation #BusinessIntelligence #SmartAutomation #SuperMegaDev\n\n\ud83d\udd17 Learn more: supermega.dev",
          "platform": "Facebook",
          "timestamp": "2025-08-13T17:58:57.158680",
          "engagement_prediction": 149,
          "reach_prediction": 1751,
          "day": 2,
          "post_number": 3
        }
      ],
      "daily_total": 3
    },
    {
      "day": 3,
      "posts": [
        {
          "content": "\u2728 Innovation in action: CEO Strategy Agent just identified $2M acquisition opportunity. That's strategic AI at work!\n\n#StrategicAI #CostOptimization #SuperMega #QualityOverQuantity\n\n\ud83d\udd17 Learn more: supermega.dev",
          "platform": "Facebook",
          "timestamp": "2025-08-13T17:58:57.158680",
          "engagement_prediction": 178,
          "reach_prediction": 1926,
          "day": 3,
          "post_number": 1
        },
        {
          "content": "\ud83d\udca1 Smart business chooses SuperMega: 91.7% more efficient, 95% cost reduction, 100% business-focused results.\n\n#StrategicAI #CostOptimization #SuperMega #QualityOverQuantity\n\n\ud83d\udd17 Learn more: supermega.dev",
          "platform": "Facebook",
          "timestamp": "2025-08-13T17:58:57.158680",
          "engagement_prediction": 173,
          "reach_prediction": 3918,
          "day": 3,
          "post_number": 2
        },
        {
          "content": "\ud83d\udca1 Smart business chooses SuperMega: 91.7% more efficient, 95% cost reduction, 100% business-focused results.\n\n#AIInnovation #BusinessIntelligence #SmartAutomation #SuperMegaDev\n\n\ud83d\udd17 Learn more: supermega.dev",
          "platform": "Facebook",
          "timestamp": "2025-08-13T17:58:57.158680",
          "engagement_prediction": 107,
          "reach_prediction": 2988,
          "day": 3,
          "post_number": 3
        },
        {
          "content": "\ud83c\udfc6 The future is here: AI agents that think strategically, act efficiently, and deliver measurable business impact.\n\n#StrategicAI #CostOptimization #SuperMega #QualityOverQuantity\n\n\ud83d\udd17 Learn more: supermega.dev",
          "platform": "Facebook",
          "timestamp": "2025-08-13T17:58:57.158680",
          "engagement_prediction": 105,
          "reach_prediction": 2286,
          "day": 3,
          "post_number": 4
        }
      ],
      "daily_total": 4
    },
    {
      "day": 4,
      "posts": [
        {
          "content": "\ud83c\udf1f SuperMega principle: One optimized agent beats ten generic ones. See the difference in our client results.\n\n#StrategicAI #CostOptimization #SuperMega #QualityOverQuantity\n\n\ud83d\udd17 Learn more: supermega.dev",
          "platform": "Facebook",
          "timestamp": "2025-08-13T17:58:57.158680",
          "engagement_prediction": 173,
          "reach_prediction": 1883,
          "day": 4,
          "post_number": 1
        },
        {
          "content": "\ud83c\udfc6 The future is here: AI agents that think strategically, act efficiently, and deliver measurable business impact.\n\n#OptimizedAI #EnterpriseAI #BusinessResults #SuperMegaPlatform\n\n\ud83d\udd17 Learn more: supermega.dev",
          "platform": "Facebook",
          "timestamp": "2025-08-13T17:58:57.158680",
          "engagement_prediction": 161,
          "reach_prediction": 1346,
          "day": 4,
          "post_number": 2
        }
      ],
      "daily_total": 2
    },
    {
      "day": 5,
      "posts": [
        {
          "content": "\u2728 Innovation in action: CEO Strategy Agent just identified $2M acquisition opportunity. That's strategic AI at work!\n\n#StrategicAI #CostOptimization #SuperMega #QualityOverQuantity\n\n\ud83d\udd17 Learn more: supermega.dev",
          "platform": "Facebook",
          "timestamp": "2025-08-13T17:58:57.158680",
          "engagement_prediction": 143,
          "reach_prediction": 1468,
          "day": 5,
          "post_number": 1
        },
        {
          "content": "\u2728 Innovation in action: CEO Strategy Agent just identified $2M acquisition opportunity. That's strategic AI at work!\n\n#OptimizedAI #EnterpriseAI #BusinessResults #SuperMegaPlatform\n\n\ud83d\udd17 Learn more: supermega.dev",
          "platform": "Facebook",
          "timestamp": "2025-08-13T17:58:57.158680",
          "engagement_prediction": 87,
          "reach_prediction": 1277,
          "day": 5,
          "post_number": 2
        },
        {
          "content": "\ud83d\udcca Live stats: 942 social engagements today, 9,336 total reach. SuperMega AI working 24/7 for better results.\n\n#OptimizedAI #EnterpriseAI #BusinessResults #SuperMegaPlatform\n\n\ud83d\udd17 Learn more: supermega.dev",
          "platform": "Facebook",
          "timestamp": "2025-08-13T17:58:57.158680",
          "engagement_prediction": 134,
          "reach_prediction": 2549,
          "day": 5,
          "post_number": 3
        }
      ],
      "daily_total": 3
    },
    {
      "day": 6,
      "posts": [
        {
          "content": "\ud83c\udfc6 The future is here: AI agents that think strategically, act efficiently, and deliver measurable business impact.\n\n#OptimizedAI #EnterpriseAI #BusinessResults #SuperMegaPlatform\n\n\ud83d\udd17 Learn more: supermega.dev",
          "platform": "Facebook",
          "timestamp": "2025-08-13T17:58:57.158680",
          "engagement_prediction": 69,
          "reach_prediction": 1548,
          "day": 6,
          "post_number": 1
        },
        {
          "content": "\ud83c\udf1f SuperMega principle: One optimized agent beats ten generic ones. See the difference in our client results.\n\n#AIInnovation #BusinessIntelligence #SmartAutomation #SuperMegaDev\n\n\ud83d\udd17 Learn more: supermega.dev",
          "platform": "Facebook",
          "timestamp": "2025-08-13T17:58:57.158680",
          "engagement_prediction": 182,
          "reach_prediction": 3141,
          "day": 6,
          "post_number": 2
        },
        {
          "content": "\ud83c\udfc6 The future is here: AI agents that think strategically, act efficiently, and deliver measurable business impact.\n\n#AIStrategy #AutomationROI #TechInnovation #SuperMegaInc\n\n\ud83d\udd17 Learn more: supermega.dev",
          "platform": "Facebook",
          "timestamp": "2025-08-13T17:58:57.158680",
          "engagement_prediction": 157,
          "reach_prediction": 2585,
          "day": 6,
          "post_number": 3
        }
      ],
      "daily_total": 3
    },
    {
      "day": 7,
      "posts": [
        {
          "content": "\u2728 Innovation in action: CEO Strategy Agent just identified $2M acquisition opportunity. That's strategic AI at work!\n\n#StrategicAI #CostOptimization #SuperMega #QualityOverQuantity\n\n\ud83d\udd17 Learn more: supermega.dev",
          "platform": "Facebook",
          "timestamp": "2025-08-13T17:58:57.158680",
          "engagement_prediction": 77,
          "reach_prediction": 1018,
          "day": 7,
          "post_number": 1
        },
        {
          "content": "\ud83c\udfaf Strategic AI beats generic automation. Our 25 agents deliver more business value than entire 300-agent platforms.\n\n#StrategicAI #CostOptimization #SuperMega #QualityOverQuantity\n\n\ud83d\udd17 Learn more: supermega.dev",
          "platform": "Facebook",
          "timestamp": "2025-08-13T17:58:57.158680",
          "engagement_prediction": 197,
          "reach_prediction": 4876,
          "day": 7,
          "post_number": 2
        },
        {
          "content": "\ud83d\udcca Live stats: 942 social engagements today, 9,336 total reach. SuperMega AI working 24/7 for better results.\n\n#AIInnovation #BusinessIntelligence #SmartAutomation #SuperMegaDev\n\n\ud83d\udd17 Learn more: supermega.dev",
          "platform": "Facebook",
          "timestamp": "2025-08-13T17:58:57.158680",
          "engagement_prediction": 196,
          "reach_prediction": 4035,
          "day": 7,
          "post_number": 3
        },
        {
          "content": "\ud83c\udf1f SuperMega principle: One optimized agent beats ten generic ones. See the difference in our client results.\n\n#AIStrategy #AutomationROI #TechInnovation #SuperMegaInc\n\n\ud83d\udd17 Learn more: supermega.dev",
          "platform": "Facebook",
          "timestamp": "2025-08-13T17:58:57.158680",
          "engagement_prediction": 194,
          "reach_prediction": 3755,
          "day": 7,
          "post_number": 4
        }
      ],
      "daily_total": 4
    }
  ],
  "total_weekly_posts": 21,
  "brand_focus": "SuperMega optimization and cost savings"
}